arnparse/__init__.py
arnparse/arnparse.py
arnparse/str_utils.py
arnparse-0.0.1.dist-info/METADATA
arnparse-0.0.1.dist-info/RECORD
arnparse-0.0.1.dist-info/WHEEL
arnparse-0.0.1.dist-info/top_level.txt
