Metadata-Version: 2.1
Name: arnparse
Version: 0.0.1
Summary: Parse ARNs using Python
Home-page: https://github.com/PokaInc/arnparse
Author: Simon-Pierre Gingras
Author-email: spgingras@poka.io
License: UNKNOWN
Download-URL: https://github.com/PokaInc/arnparse/tarball/0.0.1
Keywords: aws,arn,parse
Platform: UNKNOWN
